{
  "updated": "2026-07-14",
  "count": 43,
  "etfs": [
    {
      "ticker": "069500",
      "name": "KODEX 200",
      "category": "국내주식",
      "aum_억": 0.0,
      "dist_yield": 0.0,
      "nav": 109720,
      "price_last": 109720,
      "mom_1m": -19.5,
      "mom_3m": 23.76,
      "vol_20d": 77.79,
      "sharpe": 1.57,
      "mdd": -26.65,
      "rsi": 30.4,
      "vol_avg_억": 31459.8,
      "updated": "2026-07-14"
    },
    {
      "ticker": "122630",
      "name": "KODEX 레버리지",
      "category": "파생",
      "aum_억": 0.0,
      "dist_yield": 0.0,
      "nav": 123580,
      "price_last": 123580,
      "mom_1m": -39.13,
      "mom_3m": 36.33,
      "vol_20d": 153.97,
      "sharpe": 1.58,
      "mdd": -49.0,
      "rsi": 29.7,
      "vol_avg_억": 25673.7,
      "updated": "2026-07-14"
    },
    {
      "ticker": "360750",
      "name": "TIGER 미국S&P500",
      "category": "해외주식",
      "aum_억": 0.0,
      "dist_yield": 0.0,
      "nav": 27910,
      "price_last": 27910,
      "mom_1m": -1.1,
      "mom_3m": 11.17,
      "vol_20d": 15.01,
      "sharpe": 3.08,
      "mdd": -3.99,
      "rsi": 44.8,
      "vol_avg_억": 11494.3,
      "updated": "2026-07-14"
    },
    {
      "ticker": "252670",
      "name": "KODEX 200선물인버스2X",
      "category": "파생",
      "aum_억": 0.0,
      "dist_yield": 0.0,
      "nav": 100,
      "price_last": 100,
      "mom_1m": 35.14,
      "mom_3m": -54.34,
      "vol_20d": 157.05,
      "sharpe": -1.71,
      "mdd": -72.32,
      "rsi": 66.7,
      "vol_avg_억": 9372.8,
      "updated": "2026-07-14"
    },
    {
      "ticker": "379800",
      "name": "KODEX 미국S&P500TR",
      "category": "해외주식",
      "aum_억": 0.0,
      "dist_yield": 0.0,
      "nav": 25440,
      "price_last": 25440,
      "mom_1m": -1.15,
      "mom_3m": 10.87,
      "vol_20d": 15.6,
      "sharpe": 2.97,
      "mdd": -3.94,
      "rsi": 44.9,
      "vol_avg_억": 7976.1,
      "updated": "2026-07-14"
    },
    {
      "ticker": "233740",
      "name": "KODEX 코스닥150레버리지",
      "category": "파생",
      "aum_억": 0.0,
      "dist_yield": 0.0,
      "nav": 6930,
      "price_last": 6930,
      "mom_1m": -48.36,
      "mom_3m": -52.29,
      "vol_20d": 130.09,
      "sharpe": -2.12,
      "mdd": -61.45,
      "rsi": 29.4,
      "vol_avg_억": 7437.6,
      "updated": "2026-07-14"
    },
    {
      "ticker": "102110",
      "name": "TIGER 200",
      "category": "국내주식",
      "aum_억": 0.0,
      "dist_yield": 0.0,
      "nav": 109790,
      "price_last": 109790,
      "mom_1m": -19.46,
      "mom_3m": 23.77,
      "vol_20d": 75.95,
      "sharpe": 1.58,
      "mdd": -26.56,
      "rsi": 30.2,
      "vol_avg_억": 6802.0,
      "updated": "2026-07-14"
    },
    {
      "ticker": "395160",
      "name": "TIGER 차이나항셍테크",
      "category": "해외주식",
      "aum_억": 0.0,
      "dist_yield": 0.0,
      "nav": 41085,
      "price_last": 41085,
      "mom_1m": -22.42,
      "mom_3m": 45.74,
      "vol_20d": 101.51,
      "sharpe": 2.19,
      "mdd": -36.35,
      "rsi": 30.0,
      "vol_avg_억": 6225.4,
      "updated": "2026-07-14"
    },
    {
      "ticker": "091160",
      "name": "KODEX 반도체",
      "category": "국내주식",
      "aum_억": 0.0,
      "dist_yield": 0.0,
      "nav": 133200,
      "price_last": 133200,
      "mom_1m": -23.03,
      "mom_3m": 29.32,
      "vol_20d": 92.59,
      "sharpe": 1.68,
      "mdd": -30.8,
      "rsi": 32.9,
      "vol_avg_억": 5912.3,
      "updated": "2026-07-14"
    },
    {
      "ticker": "229200",
      "name": "KODEX 코스닥150",
      "category": "국내주식",
      "aum_억": 0.0,
      "dist_yield": 0.0,
      "nav": 13410,
      "price_last": 13410,
      "mom_1m": -26.7,
      "mom_3m": -27.81,
      "vol_20d": 68.1,
      "sharpe": -2.05,
      "mdd": -35.12,
      "rsi": 31.0,
      "vol_avg_억": 5591.0,
      "updated": "2026-07-14"
    },
    {
      "ticker": "133690",
      "name": "TIGER 미국S&P500레버리지",
      "category": "파생",
      "aum_억": 0.0,
      "dist_yield": 0.0,
      "nav": 194530,
      "price_last": 194530,
      "mom_1m": -3.84,
      "mom_3m": 18.08,
      "vol_20d": 23.81,
      "sharpe": 3.3,
      "mdd": -6.92,
      "rsi": 40.7,
      "vol_avg_억": 4376.1,
      "updated": "2026-07-14"
    },
    {
      "ticker": "459580",
      "name": "KODEX 미국AI테크TOP10SOLACTIVE",
      "category": "해외주식",
      "aum_억": 0.0,
      "dist_yield": 0.0,
      "nav": 1074595,
      "price_last": 1074595,
      "mom_1m": 0.23,
      "mom_3m": 0.72,
      "vol_20d": 0.1,
      "sharpe": -5.59,
      "mdd": 0.0,
      "rsi": 50.0,
      "vol_avg_억": 4344.5,
      "updated": "2026-07-14"
    },
    {
      "ticker": "381180",
      "name": "KODEX 미국나스닥100TR",
      "category": "해외주식",
      "aum_억": 0.0,
      "dist_yield": 0.0,
      "nav": 48860,
      "price_last": 48860,
      "mom_1m": -11.13,
      "mom_3m": 45.07,
      "vol_20d": 51.24,
      "sharpe": 3.25,
      "mdd": -17.55,
      "rsi": 35.1,
      "vol_avg_억": 1671.6,
      "updated": "2026-07-14"
    },
    {
      "ticker": "364980",
      "name": "TIGER 글로벌리튬&2차전지SOLACTIVE",
      "category": "해외주식",
      "aum_억": 0.0,
      "dist_yield": 0.0,
      "nav": 8985,
      "price_last": 8985,
      "mom_1m": -24.91,
      "mom_3m": -20.84,
      "vol_20d": 84.58,
      "sharpe": -1.01,
      "mdd": -42.42,
      "rsi": 39.1,
      "vol_avg_억": 442.0,
      "updated": "2026-07-14"
    },
    {
      "ticker": "486290",
      "name": "TIGER 미국배당다우존스",
      "category": "해외주식",
      "aum_억": 0.0,
      "dist_yield": 0.0,
      "nav": 11615,
      "price_last": 11615,
      "mom_1m": -3.86,
      "mom_3m": 16.89,
      "vol_20d": 23.51,
      "sharpe": 3.18,
      "mdd": -6.63,
      "rsi": 40.8,
      "vol_avg_억": 438.3,
      "updated": "2026-07-14"
    },
    {
      "ticker": "449450",
      "name": "SOL 미국S&P500",
      "category": "해외주식",
      "aum_억": 0.0,
      "dist_yield": 0.0,
      "nav": 50805,
      "price_last": 50805,
      "mom_1m": -23.94,
      "mom_3m": -35.85,
      "vol_20d": 73.38,
      "sharpe": -2.75,
      "mdd": -37.71,
      "rsi": 35.4,
      "vol_avg_억": 393.4,
      "updated": "2026-07-14"
    },
    {
      "ticker": "381170",
      "name": "TIGER 미국나스닥100TR",
      "category": "해외주식",
      "aum_억": 0.0,
      "dist_yield": 0.0,
      "nav": 32440,
      "price_last": 32440,
      "mom_1m": -1.53,
      "mom_3m": 10.06,
      "vol_20d": 25.11,
      "sharpe": 1.8,
      "mdd": -11.91,
      "rsi": 50.9,
      "vol_avg_억": 384.7,
      "updated": "2026-07-14"
    },
    {
      "ticker": "284430",
      "name": "KODEX 구리선물(H)",
      "category": "원자재",
      "aum_억": 0.0,
      "dist_yield": 0.0,
      "nav": 21605,
      "price_last": 21605,
      "mom_1m": -10.93,
      "mom_3m": 7.84,
      "vol_20d": 38.52,
      "sharpe": 1.06,
      "mdd": -14.97,
      "rsi": 28.4,
      "vol_avg_억": 364.4,
      "updated": "2026-07-14"
    },
    {
      "ticker": "411060",
      "name": "ACE 미국빅테크TOP7 Plus",
      "category": "해외주식",
      "aum_억": 0.0,
      "dist_yield": 0.0,
      "nav": 26765,
      "price_last": 26765,
      "mom_1m": -7.8,
      "mom_3m": -15.58,
      "vol_20d": 25.81,
      "sharpe": -3.0,
      "mdd": -16.19,
      "rsi": 39.5,
      "vol_avg_억": 318.4,
      "updated": "2026-07-14"
    },
    {
      "ticker": "091180",
      "name": "KODEX 은행",
      "category": "국내주식",
      "aum_억": 0.0,
      "dist_yield": 0.0,
      "nav": 28760,
      "price_last": 28760,
      "mom_1m": -25.23,
      "mom_3m": -7.42,
      "vol_20d": 54.08,
      "sharpe": -0.26,
      "mdd": -30.72,
      "rsi": 40.3,
      "vol_avg_억": 289.4,
      "updated": "2026-07-14"
    },
    {
      "ticker": "360200",
      "name": "ACE 미국S&P500",
      "category": "해외주식",
      "aum_억": 0.0,
      "dist_yield": 0.0,
      "nav": 28185,
      "price_last": 28185,
      "mom_1m": -1.21,
      "mom_3m": 11.03,
      "vol_20d": 15.47,
      "sharpe": 3.02,
      "mdd": -4.03,
      "rsi": 44.6,
      "vol_avg_억": 231.3,
      "updated": "2026-07-14"
    },
    {
      "ticker": "385720",
      "name": "TIGER 미국채10년선물",
      "category": "채권",
      "aum_억": 0.0,
      "dist_yield": 0.0,
      "nav": 25900,
      "price_last": 25900,
      "mom_1m": -19.65,
      "mom_3m": 20.35,
      "vol_20d": 68.82,
      "sharpe": 1.45,
      "mdd": -25.97,
      "rsi": 29.1,
      "vol_avg_억": 193.4,
      "updated": "2026-07-14"
    },
    {
      "ticker": "465580",
      "name": "TIGER 글로벌AI액티브",
      "category": "해외주식",
      "aum_억": 0.0,
      "dist_yield": 0.0,
      "nav": 24840,
      "price_last": 24840,
      "mom_1m": -0.48,
      "mom_3m": 11.47,
      "vol_20d": 26.04,
      "sharpe": 2.05,
      "mdd": -12.31,
      "rsi": 52.4,
      "vol_avg_억": 173.8,
      "updated": "2026-07-14"
    },
    {
      "ticker": "329200",
      "name": "TIGER 미국MSCI리츠",
      "category": "부동산",
      "aum_억": 0.0,
      "dist_yield": 0.0,
      "nav": 4000,
      "price_last": 4000,
      "mom_1m": -2.3,
      "mom_3m": -13.38,
      "vol_20d": 19.14,
      "sharpe": -1.98,
      "mdd": -23.1,
      "rsi": 51.7,
      "vol_avg_억": 152.3,
      "updated": "2026-07-14"
    },
    {
      "ticker": "453850",
      "name": "ACE 미국30년국채액티브",
      "category": "채권",
      "aum_억": 0.0,
      "dist_yield": 0.0,
      "nav": 7315,
      "price_last": 7315,
      "mom_1m": -2.21,
      "mom_3m": -2.18,
      "vol_20d": 9.06,
      "sharpe": -1.41,
      "mdd": -4.54,
      "rsi": 30.2,
      "vol_avg_억": 126.2,
      "updated": "2026-07-14"
    },
    {
      "ticker": "371460",
      "name": "TIGER 미국나스닥100",
      "category": "해외주식",
      "aum_억": 0.0,
      "dist_yield": 0.0,
      "nav": 11210,
      "price_last": 11210,
      "mom_1m": -13.54,
      "mom_3m": -17.82,
      "vol_20d": 35.25,
      "sharpe": -2.7,
      "mdd": -24.15,
      "rsi": 25.0,
      "vol_avg_억": 67.2,
      "updated": "2026-07-14"
    },
    {
      "ticker": "472160",
      "name": "KODEX 미국30년국채+12%프리미엄",
      "category": "채권",
      "aum_억": 0.0,
      "dist_yield": 0.0,
      "nav": 18345,
      "price_last": 18345,
      "mom_1m": -0.57,
      "mom_3m": 8.68,
      "vol_20d": 21.34,
      "sharpe": 1.61,
      "mdd": -13.71,
      "rsi": 64.0,
      "vol_avg_억": 62.0,
      "updated": "2026-07-14"
    },
    {
      "ticker": "446720",
      "name": "KINDEX 미국S&P500",
      "category": "해외주식",
      "aum_억": 0.0,
      "dist_yield": 0.0,
      "nav": 14155,
      "price_last": 14155,
      "mom_1m": -1.97,
      "mom_3m": 6.83,
      "vol_20d": 8.76,
      "sharpe": 1.96,
      "mdd": -3.19,
      "rsi": 45.6,
      "vol_avg_억": 51.0,
      "updated": "2026-07-14"
    },
    {
      "ticker": "214980",
      "name": "KODEX 단기채권PLUS",
      "category": "채권",
      "aum_억": 0.0,
      "dist_yield": 0.0,
      "nav": 114375,
      "price_last": 114375,
      "mom_1m": 0.17,
      "mom_3m": 0.49,
      "vol_20d": 0.23,
      "sharpe": -6.85,
      "mdd": -0.04,
      "rsi": 83.3,
      "vol_avg_억": 38.2,
      "updated": "2026-07-14"
    },
    {
      "ticker": "261220",
      "name": "KODEX WTI원유선물(H)",
      "category": "원자재",
      "aum_억": 0.0,
      "dist_yield": 0.0,
      "nav": 22145,
      "price_last": 22145,
      "mom_1m": 0.48,
      "mom_3m": -7.44,
      "vol_20d": 50.33,
      "sharpe": -0.34,
      "mdd": -34.13,
      "rsi": 65.0,
      "vol_avg_억": 37.2,
      "updated": "2026-07-14"
    },
    {
      "ticker": "448290",
      "name": "ACE 미국나스닥100",
      "category": "해외주식",
      "aum_억": 0.0,
      "dist_yield": 0.0,
      "nav": 17505,
      "price_last": 17505,
      "mom_1m": -0.17,
      "mom_3m": 9.85,
      "vol_20d": 9.56,
      "sharpe": 2.99,
      "mdd": -3.98,
      "rsi": 65.5,
      "vol_avg_억": 31.4,
      "updated": "2026-07-14"
    },
    {
      "ticker": "273130",
      "name": "KODEX 종합채권(AA-)액티브",
      "category": "채권",
      "aum_억": 0.0,
      "dist_yield": 0.0,
      "nav": 109435,
      "price_last": 109435,
      "mom_1m": -1.17,
      "mom_3m": -3.46,
      "vol_20d": 2.99,
      "sharpe": -4.25,
      "mdd": -3.74,
      "rsi": 35.9,
      "vol_avg_억": 27.4,
      "updated": "2026-07-14"
    },
    {
      "ticker": "132030",
      "name": "KODEX 골드선물(H)",
      "category": "원자재",
      "aum_억": 0.0,
      "dist_yield": 0.0,
      "nav": 22655,
      "price_last": 22655,
      "mom_1m": -6.83,
      "mom_3m": -16.17,
      "vol_20d": 24.37,
      "sharpe": -3.11,
      "mdd": -18.4,
      "rsi": 44.9,
      "vol_avg_억": 27.2,
      "updated": "2026-07-14"
    },
    {
      "ticker": "261240",
      "name": "KODEX 미국반도체MV",
      "category": "해외주식",
      "aum_억": 0.0,
      "dist_yield": 0.0,
      "nav": 15370,
      "price_last": 15370,
      "mom_1m": -0.87,
      "mom_3m": 1.59,
      "vol_20d": 10.62,
      "sharpe": 0.33,
      "mdd": -3.88,
      "rsi": 29.6,
      "vol_avg_억": 22.2,
      "updated": "2026-07-14"
    },
    {
      "ticker": "114260",
      "name": "KODEX 국채3년",
      "category": "채권",
      "aum_억": 0.0,
      "dist_yield": 0.0,
      "nav": 61385,
      "price_last": 61385,
      "mom_1m": -0.29,
      "mom_3m": -0.59,
      "vol_20d": 1.97,
      "sharpe": -2.52,
      "mdd": -1.29,
      "rsi": 41.6,
      "vol_avg_억": 21.8,
      "updated": "2026-07-14"
    },
    {
      "ticker": "438330",
      "name": "KODEX 인도Nifty50",
      "category": "해외주식",
      "aum_억": 0.0,
      "dist_yield": 0.0,
      "nav": 114590,
      "price_last": 114590,
      "mom_1m": -0.27,
      "mom_3m": -0.62,
      "vol_20d": 1.97,
      "sharpe": -2.71,
      "mdd": -1.18,
      "rsi": 46.2,
      "vol_avg_억": 17.0,
      "updated": "2026-07-14"
    },
    {
      "ticker": "486450",
      "name": "ACE 엔비디아채권혼합블룸버그",
      "category": "채권",
      "aum_억": 0.0,
      "dist_yield": 0.0,
      "nav": 22135,
      "price_last": 22135,
      "mom_1m": -8.95,
      "mom_3m": 2.81,
      "vol_20d": 32.83,
      "sharpe": 0.39,
      "mdd": -15.19,
      "rsi": 24.2,
      "vol_avg_억": 16.7,
      "updated": "2026-07-14"
    },
    {
      "ticker": "148070",
      "name": "KOSEF 국고채10년",
      "category": "국내주식",
      "aum_억": 0.0,
      "dist_yield": 0.0,
      "nav": 103935,
      "price_last": 103935,
      "mom_1m": -1.42,
      "mom_3m": -3.83,
      "vol_20d": 4.85,
      "sharpe": -3.07,
      "mdd": -4.59,
      "rsi": 34.5,
      "vol_avg_억": 16.2,
      "updated": "2026-07-14"
    },
    {
      "ticker": "441680",
      "name": "TIGER 인도니프티50",
      "category": "해외주식",
      "aum_억": 0.0,
      "dist_yield": 0.0,
      "nav": 11660,
      "price_last": 11660,
      "mom_1m": -0.21,
      "mom_3m": 7.32,
      "vol_20d": 18.47,
      "sharpe": 2.02,
      "mdd": -4.68,
      "rsi": 43.3,
      "vol_avg_억": 14.4,
      "updated": "2026-07-14"
    },
    {
      "ticker": "468380",
      "name": "TIGER AI코리아그로스액티브",
      "category": "국내주식",
      "aum_억": 0.0,
      "dist_yield": 0.0,
      "nav": 11865,
      "price_last": 11865,
      "mom_1m": -1.45,
      "mom_3m": 1.52,
      "vol_20d": 10.57,
      "sharpe": 0.33,
      "mdd": -4.0,
      "rsi": 28.2,
      "vol_avg_억": 8.5,
      "updated": "2026-07-14"
    },
    {
      "ticker": "308620",
      "name": "KODEX 금선물(H)",
      "category": "원자재",
      "aum_억": 0.0,
      "dist_yield": 0.0,
      "nav": 12485,
      "price_last": 12485,
      "mom_1m": -2.04,
      "mom_3m": -0.64,
      "vol_20d": 11.71,
      "sharpe": -0.57,
      "mdd": -4.91,
      "rsi": 27.3,
      "vol_avg_억": 5.2,
      "updated": "2026-07-14"
    },
    {
      "ticker": "394660",
      "name": "KODEX 미국메타버스나스닥액티브",
      "category": "해외주식",
      "aum_억": 0.0,
      "dist_yield": 0.0,
      "nav": 17500,
      "price_last": 17500,
      "mom_1m": -13.92,
      "mom_3m": 9.0,
      "vol_20d": 28.52,
      "sharpe": 1.14,
      "mdd": -18.03,
      "rsi": 26.6,
      "vol_avg_억": 3.2,
      "updated": "2026-07-14"
    },
    {
      "ticker": "457690",
      "name": "TIGER 2차전지TOP10",
      "category": "국내주식",
      "aum_억": 0.0,
      "dist_yield": 0.0,
      "nav": 10425,
      "price_last": 10425,
      "mom_1m": -0.9,
      "mom_3m": -2.8,
      "vol_20d": 3.78,
      "sharpe": -2.98,
      "mdd": -3.77,
      "rsi": 42.3,
      "vol_avg_억": 1.3,
      "updated": "2026-07-14"
    }
  ]
}